ntv_numpy/__init__.py
ntv_numpy/data_array.py
ntv_numpy/ndarray.py
ntv_numpy/ndtype.py
ntv_numpy/ntv_numpy.ini
ntv_numpy/numpy_ntv_connector.py
ntv_numpy/xarray_accessors.py
ntv_numpy/xconnector.py
ntv_numpy/xdataset.py
ntv_numpy/xndarray.py
ntv_numpy-0.2.2.dist-info/METADATA
ntv_numpy-0.2.2.dist-info/WHEEL
ntv_numpy-0.2.2.dist-info/top_level.txt
ntv_numpy-0.2.2.dist-info/RECORD
