Metadata-Version: 2.1
Name: ntv_numpy
Version: 0.2.2
Summary: NTV-NumPy : A multidimensional semantic, compact and reversible format for interoperability
Home-page: https://github.com/loco-philippe/ntv-numpy/blob/main/README.md
Author: Philippe Thomy
Author-email: philippe@loco-labs.io
Keywords: numpy,JSON-NTV,semantic JSON,development,environmental data,multidimensional
Classifier: Development Status :: 3 - Alpha
Classifier: Intended Audience :: Developers
Classifier: Topic :: Software Development :: Build Tools
Classifier: License :: OSI Approved :: MIT License
Classifier: Programming Language :: Python :: 3
Requires-Python: >=3.10, <4
Requires-Dist: json-ntv
Requires-Dist: numpy
Requires-Dist: shapely
